xolib/__init__.py
xolib/xo.py
xolib-0.1.0.dist-info/DESCRIPTION.rst
xolib-0.1.0.dist-info/METADATA
xolib-0.1.0.dist-info/RECORD
xolib-0.1.0.dist-info/WHEEL
xolib-0.1.0.dist-info/metadata.json
xolib-0.1.0.dist-info/top_level.txt
