Metadata-Version: 2.0
Name: xolib
Version: 0.1.0
Summary: Helper library for interfacing with xo-server.
Home-page: http://pypi.python.org/pypi/xolib/
Author: Vyronas Tsingaras
Author-email: vyronas@vtsingaras.me
License: LICENSE.txt
Platform: UNKNOWN
Requires-Dist: websocket-client (==0.37.0)
